_version.py
anneal-0.1.0.dist-info/METADATA
anneal-0.1.0.dist-info/WHEEL
anneal-0.1.0.dist-info/entry_points.txt
anneal-0.1.0.dist-info/licenses/LICENSE.txt
anneal/__init__.py
anneal/core/__init__.py
anneal/core/components.py
anneal/funcs/__init__.py
anneal/funcs/obj2d.py
anneal/funcs/objNd.py
anneal/mcsamplers/__init__.py
anneal/mcsamplers/chains.py
anneal/mcsamplers/sa_chains.py
anneal/quenchers/__init__.py
anneal/quenchers/boltzmann.py
anneal/viz/__init__.py
anneal/viz/viz2d.py
anneal-0.1.0.dist-info/RECORD
