Metadata-Version: 2.1
Name: anneal
Version: 0.1.0
Summary: A package for various annealing and quenching techniques
Keywords: optimization algorithms
Author-Email: Rohit Goswami <rgoswami@ieee.org>, Ruhila S <ruhila@ieee.org>, Amrita Goswami <amrita@hi.is>, Sonaly Goswami <sonaly@iitk.ac.in>, Debabrata Goswami <dgoswami@iitk.ac.in>
Maintainer-Email: Rohit Goswami <rgoswami@ieee.org>, Ruhila S <ruhila@ieee.org>, Amrita Goswami <amrita@hi.is>
License: MIT License Copyright (c) 2023 anneal core developers
Classifier: Development Status :: 4 - Beta
Classifier: Programming Language :: Python :: 3
Classifier: License :: OSI Approved :: MIT License
Classifier: Operating System :: OS Independent
Project-URL: Homepage, https://github.com/HaoZeke/anneal
Project-URL: Bug tracker, https://github.com/HaoZeke/anneal/issues
Requires-Python: >=3.10.1
Requires-Dist: click>=8.1.3
Requires-Dist: numpy>=1.24.1
Requires-Dist: matplotlib>=3.6.3
Requires-Dist: tqdm>=4.64.1
Requires-Dist: probsamplers>=0.1.0
Requires-Dist: eindir>=0.1.0
